{"nodes": [{"id": "d_brain_packages_shared_src_brain_shared_models_py", "label": "models.py", "file_type": "code", "source_file": "D:\\brain\\packages\\shared\\src\\brain\\shared\\models.py", "source_location": "L1"}, {"id": "shared_models_get_utc_now", "label": "get_utc_now()", "file_type": "code", "source_file": "D:\\brain\\packages\\shared\\src\\brain\\shared\\models.py", "source_location": "L9"}, {"id": "shared_models_document", "label": "Document", "file_type": "code", "source_file": "D:\\brain\\packages\\shared\\src\\brain\\shared\\models.py", "source_location": "L14"}, {"id": "basemodel", "label": "BaseModel", "file_type": "code", "source_file": "", "source_location": ""}, {"id": "shared_models_documentchunk", "label": "DocumentChunk", "file_type": "code", "source_file": "D:\\brain\\packages\\shared\\src\\brain\\shared\\models.py", "source_location": "L29"}, {"id": "shared_models_searchresult", "label": "SearchResult", "file_type": "code", "source_file": "D:\\brain\\packages\\shared\\src\\brain\\shared\\models.py", "source_location": "L43"}, {"id": "shared_models_chatmessage", "label": "ChatMessage", "file_type": "code", "source_file": "D:\\brain\\packages\\shared\\src\\brain\\shared\\models.py", "source_location": "L50"}, {"id": "shared_models_conversation", "label": "Conversation", "file_type": "code", "source_file": "D:\\brain\\packages\\shared\\src\\brain\\shared\\models.py", "source_location": "L59"}, {"id": "shared_models_rationale_1", "label": "Domain models and schemas for the Brain platform.", "file_type": "rationale", "source_file": "D:\\brain\\packages\\shared\\src\\brain\\shared\\models.py", "source_location": "L1"}, {"id": "shared_models_rationale_10", "label": "Return the current time in UTC with timezone info.", "file_type": "rationale", "source_file": "D:\\brain\\packages\\shared\\src\\brain\\shared\\models.py", "source_location": "L10"}, {"id": "shared_models_rationale_15", "label": "Represents a document imported into the system.", "file_type": "rationale", "source_file": "D:\\brain\\packages\\shared\\src\\brain\\shared\\models.py", "source_location": "L15"}, {"id": "shared_models_rationale_30", "label": "Represents a segment of an imported document for vector indexing.", "file_type": "rationale", "source_file": "D:\\brain\\packages\\shared\\src\\brain\\shared\\models.py", "source_location": "L30"}, {"id": "shared_models_rationale_44", "label": "Represents a hit in hybrid or semantic search.", "file_type": "rationale", "source_file": "D:\\brain\\packages\\shared\\src\\brain\\shared\\models.py", "source_location": "L44"}, {"id": "shared_models_rationale_51", "label": "Represents a message in a conversation session.", "file_type": "rationale", "source_file": "D:\\brain\\packages\\shared\\src\\brain\\shared\\models.py", "source_location": "L51"}, {"id": "shared_models_rationale_60", "label": "Represents a conversation history session.", "file_type": "rationale", "source_file": "D:\\brain\\packages\\shared\\src\\brain\\shared\\models.py", "source_location": "L60"}], "edges": [{"source": "d_brain_packages_shared_src_brain_shared_models_py", "target": "datetime", "relation": "imports_from", "context": "import", "confidence": "EXTRACTED", "source_file": "D:\\brain\\packages\\shared\\src\\brain\\shared\\models.py", "source_location": "L3", "weight": 1.0}, {"source": "d_brain_packages_shared_src_brain_shared_models_py", "target": "uuid", "relation": "imports_from", "context": "import", "confidence": "EXTRACTED", "source_file": "D:\\brain\\packages\\shared\\src\\brain\\shared\\models.py", "source_location": "L4", "weight": 1.0}, {"source": "d_brain_packages_shared_src_brain_shared_models_py", "target": "pydantic", "relation": "imports_from", "context": "import", "confidence": "EXTRACTED", "source_file": "D:\\brain\\packages\\shared\\src\\brain\\shared\\models.py", "source_location": "L6", "weight": 1.0}, {"source": "d_brain_packages_shared_src_brain_shared_models_py", "target": "shared_models_get_utc_now", "relation": "contains", "confidence": "EXTRACTED", "source_file": "D:\\brain\\packages\\shared\\src\\brain\\shared\\models.py", "source_location": "L9", "weight": 1.0}, {"source": "d_brain_packages_shared_src_brain_shared_models_py", "target": "shared_models_document", "relation": "contains", "confidence": "EXTRACTED", "source_file": "D:\\brain\\packages\\shared\\src\\brain\\shared\\models.py", "source_location": "L14", "weight": 1.0}, {"source": "shared_models_document", "target": "basemodel", "relation": "inherits", "confidence": "EXTRACTED", "source_file": "D:\\brain\\packages\\shared\\src\\brain\\shared\\models.py", "source_location": "L14", "weight": 1.0}, {"source": "d_brain_packages_shared_src_brain_shared_models_py", "target": "shared_models_documentchunk", "relation": "contains", "confidence": "EXTRACTED", "source_file": "D:\\brain\\packages\\shared\\src\\brain\\shared\\models.py", "source_location": "L29", "weight": 1.0}, {"source": "shared_models_documentchunk", "target": "basemodel", "relation": "inherits", "confidence": "EXTRACTED", "source_file": "D:\\brain\\packages\\shared\\src\\brain\\shared\\models.py", "source_location": "L29", "weight": 1.0}, {"source": "d_brain_packages_shared_src_brain_shared_models_py", "target": "shared_models_searchresult", "relation": "contains", "confidence": "EXTRACTED", "source_file": "D:\\brain\\packages\\shared\\src\\brain\\shared\\models.py", "source_location": "L43", "weight": 1.0}, {"source": "shared_models_searchresult", "target": "basemodel", "relation": "inherits", "confidence": "EXTRACTED", "source_file": "D:\\brain\\packages\\shared\\src\\brain\\shared\\models.py", "source_location": "L43", "weight": 1.0}, {"source": "d_brain_packages_shared_src_brain_shared_models_py", "target": "shared_models_chatmessage", "relation": "contains", "confidence": "EXTRACTED", "source_file": "D:\\brain\\packages\\shared\\src\\brain\\shared\\models.py", "source_location": "L50", "weight": 1.0}, {"source": "shared_models_chatmessage", "target": "basemodel", "relation": "inherits", "confidence": "EXTRACTED", "source_file": "D:\\brain\\packages\\shared\\src\\brain\\shared\\models.py", "source_location": "L50", "weight": 1.0}, {"source": "d_brain_packages_shared_src_brain_shared_models_py", "target": "shared_models_conversation", "relation": "contains", "confidence": "EXTRACTED", "source_file": "D:\\brain\\packages\\shared\\src\\brain\\shared\\models.py", "source_location": "L59", "weight": 1.0}, {"source": "shared_models_conversation", "target": "basemodel", "relation": "inherits", "confidence": "EXTRACTED", "source_file": "D:\\brain\\packages\\shared\\src\\brain\\shared\\models.py", "source_location": "L59", "weight": 1.0}, {"source": "shared_models_rationale_1", "target": "d_brain_packages_shared_src_brain_shared_models_py", "relation": "rationale_for", "confidence": "EXTRACTED", "source_file": "D:\\brain\\packages\\shared\\src\\brain\\shared\\models.py", "source_location": "L1", "weight": 1.0}, {"source": "shared_models_rationale_10", "target": "shared_models_get_utc_now", "relation": "rationale_for", "confidence": "EXTRACTED", "source_file": "D:\\brain\\packages\\shared\\src\\brain\\shared\\models.py", "source_location": "L10", "weight": 1.0}, {"source": "shared_models_rationale_15", "target": "shared_models_document", "relation": "rationale_for", "confidence": "EXTRACTED", "source_file": "D:\\brain\\packages\\shared\\src\\brain\\shared\\models.py", "source_location": "L15", "weight": 1.0}, {"source": "shared_models_rationale_30", "target": "shared_models_documentchunk", "relation": "rationale_for", "confidence": "EXTRACTED", "source_file": "D:\\brain\\packages\\shared\\src\\brain\\shared\\models.py", "source_location": "L30", "weight": 1.0}, {"source": "shared_models_rationale_44", "target": "shared_models_searchresult", "relation": "rationale_for", "confidence": "EXTRACTED", "source_file": "D:\\brain\\packages\\shared\\src\\brain\\shared\\models.py", "source_location": "L44", "weight": 1.0}, {"source": "shared_models_rationale_51", "target": "shared_models_chatmessage", "relation": "rationale_for", "confidence": "EXTRACTED", "source_file": "D:\\brain\\packages\\shared\\src\\brain\\shared\\models.py", "source_location": "L51", "weight": 1.0}, {"source": "shared_models_rationale_60", "target": "shared_models_conversation", "relation": "rationale_for", "confidence": "EXTRACTED", "source_file": "D:\\brain\\packages\\shared\\src\\brain\\shared\\models.py", "source_location": "L60", "weight": 1.0}], "raw_calls": [{"caller_nid": "shared_models_get_utc_now", "callee": "now", "is_member_call": true, "source_file": "D:\\brain\\packages\\shared\\src\\brain\\shared\\models.py", "source_location": "L11"}]}